[
  {
    "storyTitle": "pls work",
    "storyEntry": "edkjhvckwi vyugfuvyisyv. ugreuygyegwruy",
    "gifSearch": "https://media0.giphy.com/media/qQdL532ZANbjy/200.gif?cid=721f8d78yhnc5e11tbifl6ntqa7l6bu1u9r7smp56sojsyyt&rid=200.gif&ct=g",
    "id": 0,
    "dateTime": "23/03/2022, 18:06:48",
    "comments": [
      "hello",
      "evie"
    ],
    "emojiCount": [
      1,
      1,
      0
    ]
  },
  {
    "storyTitle": "pls work",
    "storyEntry": "its working now ",
    "gifSearch": "https://media4.giphy.com/media/YSYkSmLfV74dGCQRz4/200.gif?cid=721f8d78bw51md2fqd7b1ehcad44hj39rx8nx9g93wogxgob&rid=200.gif&ct=g",
    "id": 1,
    "dateTime": "23/03/2022, 18:26:12",
    "comments": [
      "pls"
    ],
    "emojiCount": [
      0,
      0,
      0
    ]
  }
]